sghmcmc/__init__.py
sghmcmc/hmc.py
sghmcmc/nsghmc_jit.py
sghmcmc/sghmc_jit.py
sghmcmc/sghmcmc.py
sghmcmc-0.2.6.dist-info/METADATA
sghmcmc-0.2.6.dist-info/RECORD
sghmcmc-0.2.6.dist-info/WHEEL
sghmcmc-0.2.6.dist-info/top_level.txt
