Metadata-Version: 2.1
Name: sghmcmc
Version: 0.2.6
Summary: long description
Home-page: https://github.com/jiangxiaoyuww/sghmc-
Author: Xiaoyu Jiang & Luman Huang
Author-email: xj35@duke.edu
License: UNKNOWN
Platform: UNKNOWN
Classifier: Programming Language :: Python :: 3
Classifier: License :: OSI Approved :: MIT License
Classifier: Operating System :: OS Independent
Requires-Dist: pandas (>=0.20.0)
Requires-Dist: numpy (>=1.8.1)
Requires-Dist: scipy (>=0.14.1)
Requires-Dist: numba
Requires-Dist: multiprocess
